tripsim/__init__.py
tripsim/sim.py
tripsim/point/__init__.py
tripsim/point/distance.py
tripsim-0.1.5.dist-info/LICENSE
tripsim-0.1.5.dist-info/METADATA
tripsim-0.1.5.dist-info/WHEEL
tripsim-0.1.5.dist-info/entry_points.txt
tripsim-0.1.5.dist-info/top_level.txt
tripsim-0.1.5.dist-info/RECORD
