Metadata-Version: 2.1
Name: tripsim
Version: 0.1.5
Summary: Simple driving trip simulator for OpenStreetMap graphs
Home-page: https://github.com/nSurely/tripsim/
Author: Inaza
Requires-Python: >=3.7
License-File: LICENSE
Requires-Dist: osmnx (==1.3.0)
Requires-Dist: networkx (==3.0)
Requires-Dist: geopy (==2.3.0)
Requires-Dist: shapely (==2.0.1)
Requires-Dist: scikit-learn (==1.2.1)
Provides-Extra: test
Requires-Dist: osmnx (==1.3.0) ; extra == 'test'
Requires-Dist: networkx (==3.0) ; extra == 'test'
Requires-Dist: geopy (==2.3.0) ; extra == 'test'
Requires-Dist: shapely (==2.0.1) ; extra == 'test'
Requires-Dist: scikit-learn (==1.2.1) ; extra == 'test'
